{
  "id": 15602,
  "loaded": true,
  "modelId": 72354,
  "name": "Infinity hat",
  "modelZoom": 1150,
  "modelRotationX": 112,
  "modelRotationY": 68,
  "modelOffsetX": 0,
  "modelOffsetY": 0,
  "stackable": 0,
  "value": 17000,
  "membersOnly": true,
  "maleEquip1": 72355,
  "femaleEquip1": 72356,
  "maleEquip2": -1,
  "femaleEquip2": -1,
  "groundOptions": [
    null,
    null,
    "take",
    null,
    null
  ],
  "inventoryOptions": [
    null,
    "Wear",
    null,
    null,
    "drop"
  ],
  "originalModelColours": [
    55977,
    695,
    17979,
    41920
  ],
  "modifiedModelColours": [
    127,
    110,
    366,
    572
  ],
  "grandExchange": false,
  "maleEquip3": -1,
  "femaleEquip3": -1,
  "maleHead1": 72357,
  "femaleHead1": 72358,
  "maleHead2": 0,
  "femaleHead2": 0,
  "modelRotationZ": 0,
  "unknownInt6": 0,
  "certId": -1,
  "certTemplateId": -1,
  "resizeX": 0,
  "resizeY": 0,
  "resizeZ": 128,
  "ambient": 0,
  "contrast": 0,
  "teamId": -1,
  "lendId": -1,
  "lendTemplateId": -1,
  "maleWearXOffset": 0,
  "maleWearYOffset": 0,
  "maleWearZOffset": 0,
  "femaleWearXOffset": 0,
  "femaleWearYOffset": 0,
  "femaleWearZOffset": 0,
  "unknownInt18": 2,
  "unknownInt19": 45,
  "unknownInt20": 0,
  "unknownInt21": 0,
  "customCursorOp1": 1,
  "customCursorId1": 51,
  "customCursorOp2": 0,
  "customCursorId2": 0,
  "wearPos": 0,
  "wearPos2": -1,
  "noted": false,
  "lended": false,
  "clientScriptData": {
    "624": 1,
    "752": 25,
    "417": 7,
    "3": 6,
    "967": 1,
    "8": 6,
    "969": 0,
    "749": 6,
    "750": 50,
    "751": 1
  },
  "data": [
    1,
    -128,
    1,
    26,
    -94,
    2,
    73,
    110,
    102,
    105,
    110,
    105,
    116,
    121,
    32,
    104,
    97,
    116,
    0,
    4,
    4,
    126,
    5,
    0,
    112,
    6,
    0,
    68,
    12,
    0,
    0,
    66,
    104,
    13,
    0,
    16,
    23,
    -128,
    1,
    26,
    -93,
    25,
    -128,
    1,
    26,
    -92,
    36,
    87,
    101,
    97,
    114,
    0,
    40,
    4,
    -38,
    -87,
    0,
    127,
    2,
    -73,
    0,
    110,
    70,
    59,
    1,
    110,
    -93,
    -64,
    2,
    60,
    90,
    -128,
    1,
    26,
    -91,
    91,
    -128,
    1,
    26,
    -90,
    127,
    2,
    0,
    45,
    -127,
    1,
    0,
    51,
    -7,
    10,
    0,
    0,
    2,
    112,
    0,
    0,
    0,
    1,
    0,
    0,
    2,
    -16,
    0,
    0,
    0,
    25,
    0,
    0,
    1,
    -95,
    0,
    0,
    0,
    7,
    0,
    0,
    0,
    3,
    0,
    0,
    0,
    6,
    0,
    0,
    3,
    -57,
    0,
    0,
    0,
    1,
    0,
    0,
    0,
    8,
    0,
    0,
    0,
    6,
    0,
    0,
    3,
    -55,
    0,
    0,
    0,
    0,
    0,
    0,
    2,
    -19,
    0,
    0,
    0,
    6,
    0,
    0,
    2,
    -18,
    0,
    0,
    0,
    50,
    0,
    0,
    2,
    -17,
    0,
    0,
    0,
    1,
    0
  ],
  "multiStackSize": 0,
  "pickSizeShift": 0,
  "bindTemplateId": -1,
  "bindId": -1,
  "wearPos3": -1
}