{
  "id": 20849,
  "loaded": true,
  "modelId": 54420,
  "name": "Fractite pickaxe",
  "modelZoom": 1250,
  "modelRotationX": 224,
  "modelRotationY": 1056,
  "modelOffsetX": -4,
  "modelOffsetY": -19,
  "stackable": 0,
  "value": 1,
  "membersOnly": false,
  "maleEquip1": 56321,
  "femaleEquip1": 56321,
  "maleEquip2": -1,
  "femaleEquip2": -1,
  "groundOptions": [
    null,
    null,
    "take",
    null,
    null
  ],
  "inventoryOptions": [
    null,
    null,
    null,
    null,
    "drop"
  ],
  "grandExchange": false,
  "maleEquip3": -1,
  "femaleEquip3": -1,
  "maleHead1": 0,
  "femaleHead1": 0,
  "maleHead2": 0,
  "femaleHead2": 0,
  "modelRotationZ": 0,
  "unknownInt6": 0,
  "certId": -1,
  "certTemplateId": -1,
  "resizeX": 0,
  "resizeY": 0,
  "resizeZ": 128,
  "ambient": 0,
  "contrast": 0,
  "teamId": -1,
  "lendId": -1,
  "lendTemplateId": -1,
  "maleWearXOffset": 0,
  "maleWearYOffset": 0,
  "maleWearZOffset": 0,
  "femaleWearXOffset": 12,
  "femaleWearYOffset": -44,
  "femaleWearZOffset": 24,
  "unknownInt18": 2,
  "unknownInt19": 45,
  "unknownInt20": 0,
  "unknownInt21": 0,
  "customCursorOp1": 0,
  "customCursorId1": 0,
  "customCursorOp2": 0,
  "customCursorId2": 0,
  "wearPos": -1,
  "wearPos2": -1,
  "noted": false,
  "lended": false,
  "clientScriptData": {
    "1397": -1
  },
  "data": [
    1,
    -128,
    0,
    -44,
    -108,
    23,
    -128,
    0,
    -36,
    1,
    25,
    -128,
    0,
    -36,
    1,
    7,
    -1,
    -4,
    8,
    -1,
    -19,
    4,
    4,
    -30,
    6,
    4,
    32,
    5,
    0,
    -32,
    2,
    70,
    114,
    97,
    99,
    116,
    105,
    116,
    101,
    32,
    112,
    105,
    99,
    107,
    97,
    120,
    101,
    0,
    126,
    3,
    -11,
    6,
    -7,
    1,
    0,
    0,
    5,
    117,
    -1,
    -1,
    -1,
    -1,
    127,
    2,
    0,
    45,
    0
  ],
  "multiStackSize": 0,
  "pickSizeShift": 0,
  "bindTemplateId": -1,
  "bindId": -1,
  "wearPos3": -1
}