{
  "id": 25285,
  "loaded": true,
  "modelId": 73045,
  "name": "Warsuit long sword",
  "modelZoom": 2000,
  "modelRotationX": 0,
  "modelRotationY": 0,
  "modelOffsetX": 0,
  "modelOffsetY": 0,
  "stackable": 0,
  "value": 0,
  "membersOnly": false,
  "maleEquip1": 73210,
  "femaleEquip1": 73210,
  "maleEquip2": -1,
  "femaleEquip2": -1,
  "groundOptions": [
    null,
    null,
    "take",
    null,
    null
  ],
  "inventoryOptions": [
    null,
    null,
    null,
    null,
    "drop"
  ],
  "originalModelColours": [
    16311,
    16323,
    16335,
    16347
  ],
  "modifiedModelColours": [
    16311,
    16323,
    16335,
    16347
  ],
  "grandExchange": false,
  "maleEquip3": -1,
  "femaleEquip3": -1,
  "maleHead1": 0,
  "femaleHead1": 0,
  "maleHead2": 0,
  "femaleHead2": 0,
  "modelRotationZ": 0,
  "unknownInt6": 0,
  "certId": -1,
  "certTemplateId": -1,
  "resizeX": 0,
  "resizeY": 0,
  "resizeZ": 128,
  "ambient": 0,
  "contrast": 0,
  "teamId": -1,
  "lendId": -1,
  "lendTemplateId": -1,
  "maleWearXOffset": 0,
  "maleWearYOffset": 0,
  "maleWearZOffset": 0,
  "femaleWearXOffset": 0,
  "femaleWearYOffset": 0,
  "femaleWearZOffset": 0,
  "unknownInt18": 0,
  "unknownInt19": 0,
  "unknownInt20": 0,
  "unknownInt21": 0,
  "customCursorOp1": 0,
  "customCursorId1": 0,
  "customCursorOp2": 0,
  "customCursorId2": 0,
  "wearPos": 3,
  "wearPos2": -1,
  "noted": false,
  "lended": false,
  "clientScriptData": {
    "2531": 2,
    "644": 2556,
    "2500": 11063,
    "1397": 1
  },
  "data": [
    1,
    -128,
    1,
    29,
    85,
    2,
    87,
    97,
    114,
    115,
    117,
    105,
    116,
    32,
    108,
    111,
    110,
    103,
    32,
    115,
    119,
    111,
    114,
    100,
    0,
    12,
    0,
    0,
    0,
    0,
    13,
    3,
    23,
    -128,
    1,
    29,
    -6,
    25,
    -128,
    1,
    29,
    -6,
    40,
    4,
    63,
    -73,
    63,
    -73,
    63,
    -61,
    63,
    -61,
    63,
    -49,
    63,
    -49,
    63,
    -37,
    63,
    -37,
    -117,
    98,
    -58,
    -7,
    4,
    0,
    0,
    9,
    -29,
    0,
    0,
    0,
    2,
    0,
    0,
    2,
    -124,
    0,
    0,
    9,
    -4,
    0,
    0,
    9,
    -60,
    0,
    0,
    43,
    55,
    0,
    0,
    5,
    117,
    0,
    0,
    0,
    1,
    0
  ],
  "multiStackSize": 0,
  "pickSizeShift": 0,
  "bindTemplateId": -1,
  "bindId": 25286,
  "wearPos3": -1
}