{
  "id": 6213,
  "loaded": true,
  "modelId": 7760,
  "name": "Mahogany pyre logs",
  "modelZoom": 1180,
  "modelRotationX": 120,
  "modelRotationY": 1852,
  "modelOffsetX": 0,
  "modelOffsetY": -7,
  "stackable": 0,
  "value": 200,
  "membersOnly": true,
  "maleEquip1": -1,
  "femaleEquip1": -1,
  "maleEquip2": -1,
  "femaleEquip2": -1,
  "groundOptions": [
    null,
    null,
    "take",
    null,
    null
  ],
  "inventoryOptions": [
    null,
    null,
    null,
    null,
    "drop"
  ],
  "originalModelColours": [
    5665,
    5784,
    5559
  ],
  "modifiedModelColours": [
    6705,
    8720,
    7050
  ],
  "grandExchange": true,
  "maleEquip3": -1,
  "femaleEquip3": -1,
  "maleHead1": 0,
  "femaleHead1": 0,
  "maleHead2": 0,
  "femaleHead2": 0,
  "modelRotationZ": 0,
  "unknownInt6": 0,
  "certId": 6214,
  "certTemplateId": -1,
  "resizeX": 0,
  "resizeY": 0,
  "resizeZ": 128,
  "ambient": 0,
  "contrast": 0,
  "teamId": -1,
  "lendId": -1,
  "lendTemplateId": -1,
  "maleWearXOffset": 0,
  "maleWearYOffset": 0,
  "maleWearZOffset": 0,
  "femaleWearXOffset": 0,
  "femaleWearYOffset": 0,
  "femaleWearZOffset": 0,
  "unknownInt18": 2,
  "unknownInt19": 45,
  "unknownInt20": 0,
  "unknownInt21": 0,
  "customCursorOp1": 0,
  "customCursorId1": 0,
  "customCursorOp2": 0,
  "customCursorId2": 0,
  "wearPos": -1,
  "wearPos2": -1,
  "noted": false,
  "lended": false,
  "clientScriptData": {
    "2195": 28
  },
  "data": [
    12,
    0,
    0,
    0,
    -56,
    1,
    30,
    80,
    8,
    -1,
    -7,
    4,
    4,
    -100,
    6,
    7,
    60,
    5,
    0,
    120,
    16,
    65,
    40,
    3,
    22,
    33,
    26,
    49,
    22,
    -104,
    34,
    16,
    21,
    -73,
    27,
    -118,
    2,
    77,
    97,
    104,
    111,
    103,
    97,
    110,
    121,
    32,
    112,
    121,
    114,
    101,
    32,
    108,
    111,
    103,
    115,
    0,
    97,
    24,
    70,
    -7,
    1,
    0,
    0,
    8,
    -109,
    0,
    0,
    0,
    28,
    127,
    2,
    0,
    45,
    0
  ],
  "multiStackSize": 0,
  "pickSizeShift": 0,
  "bindTemplateId": -1,
  "bindId": -1,
  "wearPos3": -1
}