{
  "id": 7414,
  "loaded": true,
  "modelId": 11988,
  "name": "Paddle",
  "modelZoom": 1616,
  "modelRotationX": 438,
  "modelRotationY": 243,
  "modelOffsetX": 0,
  "modelOffsetY": 4,
  "stackable": 0,
  "value": 1,
  "membersOnly": false,
  "maleEquip1": 12087,
  "femaleEquip1": 12087,
  "maleEquip2": -1,
  "femaleEquip2": -1,
  "groundOptions": [
    null,
    null,
    "take",
    null,
    null
  ],
  "inventoryOptions": [
    null,
    "Wield",
    null,
    null,
    "drop"
  ],
  "grandExchange": false,
  "maleEquip3": -1,
  "femaleEquip3": -1,
  "maleHead1": 0,
  "femaleHead1": 0,
  "maleHead2": 0,
  "femaleHead2": 0,
  "modelRotationZ": 0,
  "unknownInt6": 0,
  "certId": 7415,
  "certTemplateId": -1,
  "resizeX": 0,
  "resizeY": 0,
  "resizeZ": 128,
  "ambient": 0,
  "contrast": 0,
  "teamId": -1,
  "lendId": -1,
  "lendTemplateId": -1,
  "maleWearXOffset": 0,
  "maleWearYOffset": 0,
  "maleWearZOffset": 0,
  "femaleWearXOffset": 12,
  "femaleWearYOffset": -44,
  "femaleWearZOffset": 24,
  "unknownInt18": 2,
  "unknownInt19": 45,
  "unknownInt20": 0,
  "unknownInt21": 0,
  "customCursorOp1": 1,
  "customCursorId1": 51,
  "customCursorOp2": 0,
  "customCursorId2": 0,
  "wearPos": 3,
  "wearPos2": -1,
  "noted": false,
  "lended": false,
  "clientScriptData": {
    "686": 1
  },
  "data": [
    1,
    46,
    -44,
    8,
    0,
    4,
    4,
    6,
    80,
    6,
    0,
    -13,
    5,
    1,
    -74,
    13,
    5,
    25,
    47,
    55,
    23,
    47,
    55,
    36,
    87,
    105,
    101,
    108,
    100,
    0,
    13,
    3,
    2,
    80,
    97,
    100,
    100,
    108,
    101,
    0,
    126,
    3,
    -11,
    6,
    97,
    28,
    -9,
    -7,
    1,
    0,
    0,
    2,
    -82,
    0,
    0,
    0,
    1,
    127,
    2,
    0,
    45,
    -127,
    1,
    0,
    51,
    0
  ],
  "multiStackSize": 0,
  "pickSizeShift": 0,
  "bindTemplateId": -1,
  "bindId": -1,
  "wearPos3": -1
}