{
  "id": 9242,
  "loaded": true,
  "modelId": 16856,
  "name": "Ruby bolts (e)",
  "modelZoom": 720,
  "modelRotationX": 477,
  "modelRotationY": 117,
  "modelOffsetX": 3,
  "modelOffsetY": 5,
  "stackable": 1,
  "value": 138,
  "membersOnly": true,
  "maleEquip1": -1,
  "femaleEquip1": -1,
  "maleEquip2": -1,
  "femaleEquip2": -1,
  "groundOptions": [
    null,
    null,
    "take",
    null,
    null
  ],
  "inventoryOptions": [
    null,
    "Wield",
    null,
    null,
    "drop"
  ],
  "originalModelColours": [
    17971,
    5537,
    5532,
    5656,
    5652,
    10465
  ],
  "modifiedModelColours": [
    21559,
    21559,
    21555,
    21679,
    21675,
    563
  ],
  "grandExchange": true,
  "maleEquip3": -1,
  "femaleEquip3": -1,
  "maleHead1": 0,
  "femaleHead1": 0,
  "maleHead2": 0,
  "femaleHead2": 0,
  "modelRotationZ": 0,
  "unknownInt6": 0,
  "certId": -1,
  "certTemplateId": -1,
  "stackIds": [
    9270,
    9271,
    9272,
    9273,
    0,
    0,
    0,
    0,
    0,
    0
  ],
  "stackAmounts": [
    2,
    3,
    4,
    5,
    0,
    0,
    0,
    0,
    0,
    0
  ],
  "resizeX": 0,
  "resizeY": 0,
  "resizeZ": 128,
  "ambient": 0,
  "contrast": 0,
  "teamId": -1,
  "lendId": -1,
  "lendTemplateId": -1,
  "maleWearXOffset": 0,
  "maleWearYOffset": 0,
  "maleWearZOffset": 0,
  "femaleWearXOffset": 0,
  "femaleWearYOffset": 0,
  "femaleWearZOffset": 0,
  "unknownInt18": 2,
  "unknownInt19": 45,
  "unknownInt20": 0,
  "unknownInt21": 0,
  "customCursorOp1": 1,
  "customCursorId1": 51,
  "customCursorOp2": 0,
  "customCursorId2": 0,
  "wearPos": 13,
  "wearPos2": -1,
  "noted": false,
  "lended": false,
  "clientScriptData": {
    "2195": 3,
    "643": 1030,
    "749": 4,
    "750": 46,
    "23": 46
  },
  "data": [
    1,
    65,
    -40,
    7,
    0,
    3,
    8,
    0,
    5,
    4,
    2,
    -48,
    6,
    0,
    117,
    5,
    1,
    -35,
    36,
    87,
    105,
    101,
    108,
    100,
    0,
    13,
    13,
    11,
    16,
    100,
    36,
    54,
    0,
    2,
    101,
    36,
    55,
    0,
    3,
    102,
    36,
    56,
    0,
    4,
    103,
    36,
    57,
    0,
    5,
    12,
    0,
    0,
    0,
    -118,
    65,
    40,
    6,
    70,
    51,
    84,
    55,
    21,
    -95,
    84,
    55,
    21,
    -100,
    84,
    51,
    22,
    24,
    84,
    -81,
    22,
    20,
    84,
    -85,
    40,
    -31,
    2,
    51,
    2,
    82,
    117,
    98,
    121,
    32,
    98,
    111,
    108,
    116,
    115,
    32,
    40,
    101,
    41,
    0,
    -7,
    5,
    0,
    0,
    8,
    -109,
    0,
    0,
    0,
    3,
    0,
    0,
    2,
    -125,
    0,
    0,
    4,
    6,
    0,
    0,
    0,
    23,
    0,
    0,
    0,
    46,
    0,
    0,
    2,
    -19,
    0,
    0,
    0,
    4,
    0,
    0,
    2,
    -18,
    0,
    0,
    0,
    46,
    127,
    2,
    0,
    45,
    -127,
    1,
    0,
    51,
    0
  ],
  "multiStackSize": 0,
  "pickSizeShift": 0,
  "bindTemplateId": -1,
  "bindId": -1,
  "wearPos3": -1
}